LICENSE
README.rst
setup.py
lib/rule_engine/__init__.py
lib/rule_engine/ast.py
lib/rule_engine/builtins.py
lib/rule_engine/debug_ast.py
lib/rule_engine/debug_repl.py
lib/rule_engine/engine.py
lib/rule_engine/errors.py
lib/rule_engine/suggestions.py
lib/rule_engine/types.py
lib/rule_engine.egg-info/PKG-INFO
lib/rule_engine.egg-info/SOURCES.txt
lib/rule_engine.egg-info/dependency_links.txt
lib/rule_engine.egg-info/requires.txt
lib/rule_engine.egg-info/top_level.txt
lib/rule_engine/parser/__init__.py
lib/rule_engine/parser/base.py
lib/rule_engine/parser/parsetab.py
lib/rule_engine/parser/utilities.py