Metadata-Version: 2.2
Name: rule-engine
Version: 4.5.1
Summary: A lightweight, optionally typed expression language with a custom grammar for matching arbitrary Python objects.
Home-page: https://github.com/zeroSteiner/rule-engine
Author: Spencer McIntyre
Author-email: zeroSteiner@gmail.com
Maintainer: Spencer McIntyre
Maintainer-email: zeroSteiner@gmail.com
License: BSD
Classifier: Development Status :: 5 - Production/Stable
Classifier: Environment :: Console
Classifier: Intended Audience :: Developers
Classifier: License :: OSI Approved :: BSD License
Classifier: Operating System :: OS Independent
Classifier: Programming Language :: Python :: 3.6
Classifier: Programming Language :: Python :: 3.7
Classifier: Programming Language :: Python :: 3.8
Classifier: Programming Language :: Python :: 3.9
Classifier: Programming Language :: Python :: 3.10
Classifier: Programming Language :: Python :: 3.11
Classifier: Programming Language :: Python :: 3.12
Classifier: Topic :: Software Development :: Libraries :: Python Modules
License-File: LICENSE
Requires-Dist: ply>=3.9
Requires-Dist: python-dateutil~=2.7
Dynamic: author
Dynamic: author-email
Dynamic: classifier
Dynamic: description
Dynamic: description-content-type
Dynamic: home-page
Dynamic: license
Dynamic: maintainer
Dynamic: maintainer-email
Dynamic: requires-dist
Dynamic: summary
